Workbook
Name chartTableData: #REF!
Name chartTableHeader: #REF!
Name chartTableName: #REF!
Name chartTableTotal: #REF!
Name CLS: #REF!
Name DAT: #REF!
Name filterValues: #REF!
Name phTableData: #REF!
Name phTableHeader: #REF!
Name phTableName: #REF!
Name sheetHeader: #REF!
Name statPriceChangeTableData: #REF!
Name statPriceChangeTableHeader: #REF!
Name statPriceTableData: #REF!
Name statPriceTableHeader: #REF!
Name statTableName: #REF!
Name statUpDownTableData: #REF!
Name statUpDownTableHeader: #REF!
Name statVolumeTableData: #REF!
Name statVolumeTableHeader: #REF!

Sheet DETAILS
B1: Engro Polymer & Chemicals ltd.
C6: Name | D6: Abdul Rahim Shaikh
C7: ERP | D7: 26570
C8: Financial Modeling Project # 2
C9: Class | D9: 97378
C10: Submitted to | D10: Sir Irfan Ahmed

Sheet Assumptions
A2: Engro Polymer & Chemicals ltd.
C6: Historical Data (000s) | H6: Forecasted Data (000s)
B7: Assumptions | C7: 2019 | D7: 2020 | E7: 2021 | F7: 2022 | G7: 2023 | H7: 2024 | I7: 2025 | J7: 2026 | K7: 2027 | L7: 2028
A8: Property Plant and equipment | C8: =SUM(C9:C11) -> 31064266 | D8: =SUM(D9:D11) -> 36186640 | E8: =SUM(E9:E11) -> 36792644 | F8: 41004218 | G8: 44794643 | H8: ='Depreciation schedule'!H2 -> 50177016 | I8: ='Depreciation schedule'!I2 -> 52227831 | J8: ='Depreciation schedule'!J2 -> 54002526 | K8: ='Depreciation schedule'!K2 -> 59152246 | L8: ='Depreciation schedule'!L2 -> 61423110
A9: Operating assets | C9: 18304481 | D9: 19285257 | E9: 31388709 | F9: 34375626 | G9: 34567240 | H9: ='Depreciation schedule'!H3 -> 38184094 | I9: ='Depreciation schedule'!I3 -> 41009356 | J9: ='Depreciation schedule'!J3 -> 44477084 | K9: ='Depreciation schedule'!K3 -> 48906953 | L9: ='Depreciation schedule'!L3 -> 50373110
A10: Capital work in progress | C10: 12695993 | D10: 16837591 | E10: 5185100 | F10: 6416479 | G10: 9981976 | H10: ='Depreciation schedule'!H4 -> 11832130 | I10: ='Depreciation schedule'!I4 -> 11038283 | J10: ='Depreciation schedule'!J4 -> 9321969.9 | K10: ='Depreciation schedule'!K4 -> 10044894 | L10: ='Depreciation schedule'!L4 -> 10851944
A11: Capital Spares | B11: Moving average | C11: 63792 | D11: 63792 | E11: 218835 | F11: 212113 | G11: 245427 | H11: ='Depreciation schedule'!H5 -> 160791.8 | I11: ='Depreciation schedule'!I5 -> 180191.76 | J11: ='Depreciation schedule'!J5 -> 203471.71 | K11: ='Depreciation schedule'!K5 -> 200399.05 | L11: ='Depreciation schedule'!L5 -> 198056.27
A14: Operating Assets
A15: Leasehold land
A16: Gross carrying value - As at January 1,(Current Year) | B16: Depreciation schedule
A17: Cost | C17: 194127 | D17: 1133655 | E17: 1152179 | F17: 1152179 | G17: 1152179 | H17: ='Depreciation schedule'!H9 -> 1175179 | I17: ='Depreciation schedule'!I9 -> 1175179 | J17: ='Depreciation schedule'!J9 -> 1175179 | K17: ='Depreciation schedule'!K9 -> 1198638.1 | L17: ='Depreciation schedule'!L9 -> 1198638.1
A18: Accumulated depreciation | C18: -52666 | D18: -85617 | E18: -124589 | F18: -164047 | G18: -203504 | H18: ='Depreciation schedule'!H10 -> -243412 | I18: ='Depreciation schedule'!I10 -> -282269.1 | J18: ='Depreciation schedule'!J10 -> -321126.2 | K18: ='Depreciation schedule'!K10 -> -359983.3 | L18: ='Depreciation schedule'!L10 -> -399616.07
A19: Net book value | C19: =SUM(C17:C18) -> 141461 | D19: =SUM(D17:D18) -> 1048038 | E19: =SUM(E17:E18) -> 1027590 | F19: 988132 | G19: 948675 | H19: ='Depreciation schedule'!H11 -> 931767 | I19: ='Depreciation schedule'!I11 -> 892909.9 | J19: ='Depreciation schedule'!J11 -> 854052.8 | K19: ='Depreciation schedule'!K11 -> 838654.83 | L19: ='Depreciation schedule'!L11 -> 799022.06
A20: Year ended December 31, Current | H20: ='Depreciation schedule'!H12 -> 0 | I20: ='Depreciation schedule'!I12 -> 0 | J20: ='Depreciation schedule'!J12 -> 0 | K20: ='Depreciation schedule'!K12 -> 0 | L20: ='Depreciation schedule'!L12 -> 0
A21: Net carrying value | H21: ='Depreciation schedule'!H13 -> 0 | I21: ='Depreciation schedule'!I13 -> 0 | J21: ='Depreciation schedule'!J13 -> 0 | K21: ='Depreciation schedule'!K13 -> 0 | L21: ='Depreciation schedule'!L13 -> 0
A22: Opening net book value | C22: =C19 -> 141461 | D22: 1048038 | E22: =E19 -> 1027590 | F22: 988132 | G22: 948675 | H22: ='Depreciation schedule'!H14 -> 931767 | I22: ='Depreciation schedule'!I14 -> 892909.9 | J22: ='Depreciation schedule'!J14 -> 854052.8 | K22: ='Depreciation schedule'!K14 -> 838654.83 | L22: ='Depreciation schedule'!L14 -> 799022.06
A23: Additions | C23: 939528 | D23: 18524 | G23: 23000 | H23: ='Depreciation schedule'!H15 -> 0 | I23: ='Depreciation schedule'!I15 -> 0 | J23: ='Depreciation schedule'!J15 -> 23459.13 | K23: ='Depreciation schedule'!K15 -> 0 | L23: ='Depreciation schedule'!L15 -> 0
A24: Disposals / write-offs | D24: - | G24: - | H24: ='Depreciation schedule'!H16 -> 0 | I24: ='Depreciation schedule'!I16 -> 0 | J24: ='Depreciation schedule'!J16 -> 0 | K24: ='Depreciation schedule'!K16 -> 0 | L24: ='Depreciation schedule'!L16 -> 0
A25: Cost | C25: 0 | D25: 0 | E25: 0 | F25: 0 | G25: 0 | H25: 0 | I25: 0 | J25: ='Depreciation schedule'!J17 -> 0 | K25: ='Depreciation schedule'!K17 -> 0 | L25: ='Depreciation schedule'!L17 -> 0
A26: Accumulated depreciation | D26: - | G26: - | H26: ='Depreciation schedule'!H18 -> 0 | I26: ='Depreciation schedule'!I18 -> 0 | J26: ='Depreciation schedule'!J18 -> 0 | K26: ='Depreciation schedule'!K18 -> 0 | L26: ='Depreciation schedule'!L18 -> 0
A27: Depreciation charge | C27: -32931 | D27: -38972 | E27: -39458 | F27: -39457 | G27: -39908 | H27: ='Depreciation schedule'!H19 -> -38857.098 | I27: ='Depreciation schedule'!I19 -> -38857.098 | J27: ='Depreciation schedule'!J19 -> -38857.098 | K27: ='Depreciation schedule'!K19 -> -39632.771 | L27: ='Depreciation schedule'!L19 -> -39632.771
A28: Net book value | C28: =SUM(C22:C27) -> 1048058 | D28: =SUM(D22:D27) -> 1027590 | E28: =SUM(E22:E27) -> 988132 | F28: 948675 | G28: 931767 | H28: ='Depreciation schedule'!H20 -> 892909.9 | I28: ='Depreciation schedule'!I20 -> 854052.8 | J28: ='Depreciation schedule'!J20 -> 838654.83 | K28: ='Depreciation schedule'!K20 -> 799022.06 | L28: ='Depreciation schedule'!L20 -> 759389.29
A29: Gross carrying value - As at December 31, Current Year | H29: ='Depreciation schedule'!H21 -> 0 | I29: ='Depreciation schedule'!I21 -> 0 | J29: ='Depreciation schedule'!J21 -> 0 | K29: ='Depreciation schedule'!K21 -> 0 | L29: ='Depreciation schedule'!L21 -> 0
A30: Cost | C30: 1133655 | D30: 1152179 | E30: 1152179 | F30: 1152179 | G30: 1175179 | H30: ='Depreciation schedule'!H22 -> 1175179 | I30: ='Depreciation schedule'!I22 -> 1175179 | J30: ='Depreciation schedule'!J22 -> 1198638.1 | K30: ='Depreciation schedule'!K22 -> 1198638.1 | L30: ='Depreciation schedule'!L22 -> 1198638.1
A31: Accumulated depreciation | C31: -85617 | D31: -124589 | E31: -164047 | F31: -203504 | G31: -243412 | H31: ='Depreciation schedule'!H23 -> -282269.1 | I31: ='Depreciation schedule'!I23 -> -321126.2 | J31: ='Depreciation schedule'!J23 -> -359983.3 | K31: ='Depreciation schedule'!K23 -> -399616.07 | L31: ='Depreciation schedule'!L23 -> -439248.84
A32: Net book value | C32: =SUM(C30:C31) -> 1048038 | D32: =SUM(D30:D31) -> 1027590 | E32: =SUM(E30:E31) -> 988132 | F32: 948675 | G32: 931767 | H32: ='Depreciation schedule'!H24 -> 892909.9 | I32: ='Depreciation schedule'!I24 -> 854052.8 | J32: ='Depreciation schedule'!J24 -> 838654.83 | K32: ='Depreciation schedule'!K24 -> 799022.06 | L32: ='Depreciation schedule'!L24 -> 759389.29
A35: Buildings on leasehold land
A36: Gross carrying value - As at January 1,(Current Year) | B36: Depreciation Schedule
A37: Cost | C37: 552959 | D37: 551560 | E37: 608098 | F37: 1253027 | G37: 1212885 | H37: ='Depreciation schedule'!H29 -> 1299054 | I37: ='Depreciation schedule'!I29 -> 2676788.5 | J37: ='Depreciation schedule'!J29 -> 2577736.1 | K37: ='Depreciation schedule'!K29 -> 2760870.4 | L37: ='Depreciation schedule'!L29 -> 5688960
A38: Accumulated depreciation | C38: -169358 | D38: -198464 | E38: -222189 | F38: -266271 | G38: -252888 | H38: ='Depreciation schedule'!H30 -> -309378 | I38: ='Depreciation schedule'!I30 -> -360913.32 | J38: ='Depreciation schedule'!J30 -> -467105.34 | K38: ='Depreciation schedule'!K30 -> -569367.8 | L38: ='Depreciation schedule'!L30 -> -678895.47
A39: Net book value | C39: =SUM(C37:C38) -> 383601 | D39: =SUM(D37:D38) -> 353096 | E39: =SUM(E37:E38) -> 385909 | F39: 986756 | G39: 959997 | H39: ='Depreciation schedule'!H31 -> 989676 | I39: ='Depreciation schedule'!I31 -> 2315875.2 | J39: ='Depreciation schedule'!J31 -> 2110630.7 | K39: ='Depreciation schedule'!K31 -> 2191502.6 | L39: ='Depreciation schedule'!L31 -> 5010064.5
A40: Year ended December 31, Current | H40: ='Depreciation schedule'!H32 -> 0 | I40: ='Depreciation schedule'!I32 -> 0 | J40: ='Depreciation schedule'!J32 -> 0 | K40: ='Depreciation schedule'!K32 -> 0 | L40: ='Depreciation schedule'!L32 -> 0
A41: Net carrying value | H41: ='Depreciation schedule'!H33 -> 0 | I41: ='Depreciation schedule'!I33 -> 0 | J41: ='Depreciation schedule'!J33 -> 0 | K41: ='Depreciation schedule'!K33 -> 0 | L41: ='Depreciation schedule'!L33 -> 0
A42: Opening net book value | C42: =C39 -> 383601 | D42: 353096 | E42: =E39 -> 385909 | F42: 986756 | G42: 959997 | H42: ='Depreciation schedule'!H34 -> 989676 | I42: ='Depreciation schedule'!I34 -> 2315875.2 | J42: ='Depreciation schedule'!J34 -> 2110630.7 | K42: ='Depreciation schedule'!K34 -> 2191502.6 | L42: ='Depreciation schedule'!L34 -> 5010064.5
A43: Additions | C43: 1980 | D43: 56538 | E43: 644929 | F43: 22975 | G43: 86169 | H43: ='Depreciation schedule'!H35 -> 1377734.5 | I43: ='Depreciation schedule'!I35 -> 49080.519 | J43: ='Depreciation schedule'!J35 -> 183134.38 | K43: ='Depreciation schedule'!K35 -> 2928089.6 | L43: ='Depreciation schedule'!L35 -> 104310.49
A44: Disposals / write-offs | D44: - | F44: -63117 | G44: - | H44: ='Depreciation schedule'!H36 -> 0 | I44: ='Depreciation schedule'!I36 -> 0 | J44: ='Depreciation schedule'!J36 -> 0 | K44: ='Depreciation schedule'!K36 -> 0 | L44: ='Depreciation schedule'!L36 -> 0
A45: Cost | C45: -3379 | D45: 0 | E45: 0 | F45: 63117 | G45: 0 | H45: 0 | I45: ='Depreciation schedule'!I37 -> -148132.97 | J45: ='Depreciation schedule'!J37 -> 0 | K45: ='Depreciation schedule'!K37 -> 0 | L45: ='Depreciation schedule'!L37 -> -320464.47
A46: Accumulated depreciation | C46: 596 | D46: - | F46: - | G46: - | H46: ='Depreciation schedule'!H38 -> 0 | I46: ='Depreciation schedule'!I38 -> 148132.97 | J46: ='Depreciation schedule'!J38 -> 0 | K46: ='Depreciation schedule'!K38 -> 0 | L46: ='Depreciation schedule'!L38 -> 320464.47
A47: Depreciation charge | C47: -29702 | D47: -23725 | E47: -44082 | F47: -49734 | G47: -56490 | H47: ='Depreciation schedule'!H39 -> -51535.324 | I47: ='Depreciation schedule'!I39 -> -106192.02 | J47: ='Depreciation schedule'!J39 -> -102262.46 | K47: ='Depreciation schedule'!K39 -> -109527.67 | L47: ='Depreciation schedule'!L39 -> -225689.15
A48: Net book value | C48: =SUM(C42:C47) -> 353096 | D48: 385909 | E48: =SUM(E42:E47) -> 986756 | F48: 959997 | G48: 989676 | H48: ='Depreciation schedule'!H40 -> 2315875.2 | I48: ='Depreciation schedule'!I40 -> 2258763.7 | J48: ='Depreciation schedule'!J40 -> 2191502.6 | K48: ='Depreciation schedule'!K40 -> 5010064.5 | L48: ='Depreciation schedule'!L40 -> 4888685.9
A49: Gross carrying value - As at December 31, Current Year | H49: ='Depreciation schedule'!H41 -> 0 | I49: ='Depreciation schedule'!I41 -> 0 | J49: ='Depreciation schedule'!J41 -> 0 | K49: ='Depreciation schedule'!K41 -> 0 | L49: ='Depreciation schedule'!L41 -> 0
A50: Cost | C50: 551560 | D50: 608098 | E50: 1253027 | F50: 1212885 | G50: 1299054 | H50: ='Depreciation schedule'!H42 -> 2676788.5 | I50: ='Depreciation schedule'!I42 -> 2577736.1 | J50: ='Depreciation schedule'!J42 -> 2760870.4 | K50: ='Depreciation schedule'!K42 -> 5688960 | L50: ='Depreciation schedule'!L42 -> 5472806
A51: Accumulated depreciation | C51: -198464 | D51: -222189 | E51: -266271 | F51: -252888 | G51: -309378 | H51: ='Depreciation schedule'!H43 -> -360913.32 | I51: ='Depreciation schedule'!I43 -> -467105.34 | J51: ='Depreciation schedule'!J43 -> -569367.8 | K51: ='Depreciation schedule'!K43 -> -678895.47 | L51: ='Depreciation schedule'!L43 -> -904584.62
A52: Net book value | C52: =SUM(C50:C51) -> 353096 | D52: 385909 | E52: =SUM(E50:E51) -> 986756 | F52: 959997 | G52: 989676 | H52: ='Depreciation schedule'!H44 -> 2315875.2 | I52: ='Depreciation schedule'!I44 -> 2110630.7 | J52: ='Depreciation schedule'!J44 -> 2191502.6 | K52: ='Depreciation schedule'!K44 -> 5010064.5 | L52: ='Depreciation schedule'!L44 -> 4568221.4
A54: Plant and Machinery
A55: Gross carrying value - As at January 1,(Current Year) | B55: Depreciation Schedule
A56: Cost | C56: 26398096 | D56: 28025363 | E56: 30076319 | F56: 42877113 | G56: 47846447 | H56: ='Depreciation schedule'!H48 -> 50806667 | I56: ='Depreciation schedule'!I48 -> 55769328 | J56: ='Depreciation schedule'!J48 -> 61399067 | K56: ='Depreciation schedule'!K48 -> 67744563 | L56: ='Depreciation schedule'!L48 -> 72758988
A57: Accumulated depreciation | C57: -10701284 | D57: -11599581 | E57: -12732611 | F57: -14204304 | G57: -16193705 | H57: ='Depreciation schedule'!H49 -> -19201926 | I57: ='Depreciation schedule'!I49 -> -21828396 | J57: ='Depreciation schedule'!J49 -> -24704888 | K57: ='Depreciation schedule'!K49 -> -27873327 | L57: ='Depreciation schedule'!L49 -> -31295621
A58: Net book value | C58: =SUM(C56:C57) -> 15696812 | D58: =SUM(D56:D57) -> 16425782 | E58: =SUM(E56:E57) -> 17343708 | F58: =SUM(F56:F57) -> 28672809 | G58: 31652742 | H58: ='Depreciation schedule'!H50 -> 31604741 | I58: ='Depreciation schedule'!I50 -> 33940932 | J58: ='Depreciation schedule'!J50 -> 36694179 | K58: ='Depreciation schedule'!K50 -> 39871236 | L58: ='Depreciation schedule'!L50 -> 41463367
A59: Year ended December 31, Current | H59: ='Depreciation schedule'!H51 -> 0 | I59: ='Depreciation schedule'!I51 -> 0 | J59: ='Depreciation schedule'!J51 -> 0 | K59: ='Depreciation schedule'!K51 -> 0 | L59: ='Depreciation schedule'!L51 -> 0
A60: Net carrying value | H60: ='Depreciation schedule'!H52 -> 0 | I60: ='Depreciation schedule'!I52 -> 0 | J60: ='Depreciation schedule'!J52 -> 0 | K60: ='Depreciation schedule'!K52 -> 0 | L60: ='Depreciation schedule'!L52 -> 0
A61: Opening net book value | C61: 15696812 | D61: 16425782 | E61: 17343708 | F61: 28672809 | G61: 31652742 | H61: ='Depreciation schedule'!H53 -> 31604741 | I61: ='Depreciation schedule'!I53 -> 33940932 | J61: ='Depreciation schedule'!J53 -> 36694179 | K61: ='Depreciation schedule'!K53 -> 39871236 | L61: ='Depreciation schedule'!L53 -> 41463367
A62: Additions | C62: 1627267 | D62: 2050956 | E62: 13000848 | F62: 5174012 | G62: 2960220 | H62: ='Depreciation schedule'!H54 -> 4962660.6 | I62: ='Depreciation schedule'!I54 -> 5629739.3 | J62: ='Depreciation schedule'!J54 -> 6345496 | K62: ='Depreciation schedule'!K54 -> 5014425.6 | L62: ='Depreciation schedule'!L54 -> 4982508.3
A63: Disposals / write-offs | C63: - | D63: - | E63: - | F63: - | G63: - | H63: ='Depreciation schedule'!H55 -> 0 | I63: ='Depreciation schedule'!I55 -> 0 | J63: ='Depreciation schedule'!J55 -> 0 | K63: ='Depreciation schedule'!K55 -> 0 | L63: ='Depreciation schedule'!L55 -> 0
A64: Cost | C64: 0 | D64: 0 | E64: -200054 | F64: -204678 | G64: 0 | H64: ='Depreciation schedule'!H56 -> 0 | I64: ='Depreciation schedule'!I56 -> 0 | J64: ='Depreciation schedule'!J56 -> 0 | K64: ='Depreciation schedule'!K56 -> -285884.01 | L64: ='Depreciation schedule'!L56 -> 0
A65: Accumulated depreciation | C65: - | D65: - | E65: 127089 | F65: 204678 | G65: - | H65: ='Depreciation schedule'!H57 -> 0 | I65: ='Depreciation schedule'!I57 -> 0 | J65: ='Depreciation schedule'!J57 -> 0 | K65: ='Depreciation schedule'!K57 -> 285884.01 | L65: ='Depreciation schedule'!L57 -> 0
A66: Depreciation charge | C66: -898297 | D66: -1133030 | E66: -1598782 | F66: -2194079 | G66: -2676454 | H66: ='Depreciation schedule'!H59 -> -2626469.7 | I66: ='Depreciation schedule'!I59 -> -2876492.4 | J66: ='Depreciation schedule'!J59 -> -3168438.8 | K66: ='Depreciation schedule'!K59 -> -3422294.1 | L66: ='Depreciation schedule'!L59 -> -3573957.9
A67: Net book value | C67: =SUM(C61:C66) -> 16425782 | D67: =SUM(D61:D66) -> 17343708 | E67: =SUM(E61:E66) -> 28672809 | F67: =SUM(F61:F66) -> 31652742 | G67: 31936508 | H67: ='Depreciation schedule'!H60 -> 33940932 | I67: ='Depreciation schedule'!I60 -> 36694179 | J67: ='Depreciation schedule'!J60 -> 39871236 | K67: ='Depreciation schedule'!K60 -> 41463367 | L67: ='Depreciation schedule'!L60 -> 42871918
A68: Gross carrying value - As at December 31, Current Year | H68: ='Depreciation schedule'!H61 -> 0 | I68: ='Depreciation schedule'!I61 -> 0 | J68: ='Depreciation schedule'!J61 -> 0 | K68: ='Depreciation schedule'!K61 -> 0 | L68: ='Depreciation schedule'!L61 -> 0
A69: Cost | C69: 28025363 | D69: 30076319 | E69: 42877113 | F69: 47846447 | G69: 50806667 | H69: ='Depreciation schedule'!H62 -> 55769328 | I69: ='Depreciation schedule'!I62 -> 61399067 | J69: ='Depreciation schedule'!J62 -> 67744563 | K69: ='Depreciation schedule'!K62 -> 72758988 | L69: ='Depreciation schedule'!L62 -> 77741497
A70: Accumulated depreciation | C70: -11599581 | D70: -12732611 | E70: -14204304 | F70: -16193705 | G70: -18870159 | H70: ='Depreciation schedule'!H63 -> -21828396 | I70: ='Depreciation schedule'!I63 -> -24704888 | J70: ='Depreciation schedule'!J63 -> -27873327 | K70: ='Depreciation schedule'!K63 -> -31295621 | L70: ='Depreciation schedule'!L63 -> -34869579
A71: Net book value | C71: =SUM(C69:C70) -> 16425782 | D71: =SUM(D69:D70) -> 17343708 | E71: =SUM(E69:E70) -> 28672809 | F71: =SUM(F69:F70) -> 31652742 | G71: 31936508 | H71: ='Depreciation schedule'!H64 -> 33940932 | I71: ='Depreciation schedule'!I64 -> 36694179 | J71: ='Depreciation schedule'!J64 -> 39871236 | K71: ='Depreciation schedule'!K64 -> 41463367 | L71: ='Depreciation schedule'!L64 -> 42871918
A73: Pipelines
A74: Gross carrying value - As at January 1,(Current Year) | B74: Depreciation Schedule
A75: Cost | C75: =SUM(398968,26122,50315,33849) -> 509254 | D75: =SUM(398968,26122,50315,98288,33849) -> 607542 | E75: =SUM(398968,26122,50135,100287,33849) -> 609361 | F75: =574407+33849 -> 608256 | G75: ='Depreciation schedule'!G70 -> 725651.77 | H75: ='Depreciation schedule'!H70 -> 728039.39 | I75: ='Depreciation schedule'!I70 -> 726504.58 | J75: ='Depreciation schedule'!J70 -> 866722.78 | K75: ='Depreciation schedule'!K70 -> 869574.57 | L75: ='Depreciation schedule'!L70 -> 867741.38
A76: Accumulated depreciation | C76: =-SUM(245573,25021,2866,18242) -> -291702 | D76: =-SUM(258471,25029,24056,253,19714) -> -327523 | E76: =-(SUM(271337,25374,25823,3300,21185)) -> -347019 | F76: =-343384-22656 -> -366040 | G76: ='Depreciation schedule'!G71 -> -386984 | H76: ='Depreciation schedule'!H71 -> -406949 | I76: ='Depreciation schedule'!I71 -> -428424.51 | J76: ='Depreciation schedule'!J71 -> -428424.51 | K76: ='Depreciation schedule'!K71 -> -428424.51 | L76: ='Depreciation schedule'!L71 -> -428424.51
A77: Net book value | C77: =SUM(C75:C76) -> 217552 | D77: =SUM(D75:D76) -> 280019 | E77: =SUM(E75:E76) -> 262342 | F77: =SUM(F75:F76) -> 242216 | G77: ='Depreciation schedule'!G72 -> 338667.77 | H77: ='Depreciation schedule'!H72 -> 321090.39 | I77: ='Depreciation schedule'!I72 -> 298080.06 | J77: ='Depreciation schedule'!J72 -> 438298.27 | K77: ='Depreciation schedule'!K72 -> 441150.05 | L77: ='Depreciation schedule'!L72 -> 439316.86
A78: Year ended December 31, Current | G78: ='Depreciation schedule'!G73 -> 0 | H78: ='Depreciation schedule'!H73 -> 0 | I78: ='Depreciation schedule'!I73 -> 0 | J78: ='Depreciation schedule'!J73 -> 0 | K78: ='Depreciation schedule'!K73 -> 0 | L78: ='Depreciation schedule'!L73 -> 0
A79: Net carrying value | G79: ='Depreciation schedule'!G74 -> 0 | H79: ='Depreciation schedule'!H74 -> 0 | I79: ='Depreciation schedule'!I74 -> 0 | J79: ='Depreciation schedule'!J74 -> 0 | K79: ='Depreciation schedule'!K74 -> 0 | L79: ='Depreciation schedule'!L74 -> 0
A80: Opening net book value | C80: =SUM(153395,1101,28449,15607) -> 198552 | D80: =SUM(140497,1093,26259,98035,14135) -> 280019 | E80: =SUM(127631,748,24492,96987,12664) -> 262522 | F80: =F77 -> 242216 | G80: ='Depreciation schedule'!G75 -> 338667.77 | H80: ='Depreciation schedule'!H75 -> 321090.39 | I80: ='Depreciation schedule'!I75 -> 298080.06 | J80: ='Depreciation schedule'!J75 -> 438298.27 | K80: ='Depreciation schedule'!K75 -> 441150.05 | L80: ='Depreciation schedule'!L75 -> 439316.86
A81: Additions | C81: 98288 | D81: 1999 | F81: 0 | G81: ='Depreciation schedule'!G76 -> 2387.6175 | H81: ='Depreciation schedule'!H76 -> 0 | I81: ='Depreciation schedule'!I76 -> 140218.21 | J81: ='Depreciation schedule'!J76 -> 2851.7845 | K81: ='Depreciation schedule'!K76 -> 0 | L81: ='Depreciation schedule'!L76 -> 167477.46
A82: Disposals / write-offs | F82: 0 | G82: ='Depreciation schedule'!G77 -> 0 | H82: ='Depreciation schedule'!H77 -> 0 | I82: ='Depreciation schedule'!I77 -> 0 | J82: ='Depreciation schedule'!J77 -> 0 | K82: ='Depreciation schedule'!K77 -> 0 | L82: ='Depreciation schedule'!L77 -> 0
A83: Cost | C83: 0 | D83: 0 | E83: =-SUM(993,292) -> -1285 | F83: 0 | G83: ='Depreciation schedule'!G78 -> 0 | H83: ='Depreciation schedule'!H78 -> -1534.8116 | I83: ='Depreciation schedule'!I78 -> 0 | J83: ='Depreciation schedule'!J78 -> 0 | K83: ='Depreciation schedule'!K78 -> -1833.1881 | L83: ='Depreciation schedule'!L78 -> 0
A84: Accumulated depreciation | E84: =802+157 -> 959 | F84: 0 | G84: ='Depreciation schedule'!G79 -> 0 | H84: ='Depreciation schedule'!H79 -> 1124.554 | I84: ='Depreciation schedule'!I79 -> 0 | J84: ='Depreciation schedule'!J79 -> 0 | K84: ='Depreciation schedule'!K79 -> 1183.899 | L84: ='Depreciation schedule'!L79 -> 0
A85: Depreciation charge | C85: =-SUM(12898,8,2190,253,1472) -> -16821 | D85: =-SUM(12886,345,1767,3047,1471) -> -19516 | E85: =-SUM(12885,345,4112,1167,1471) -> -19980 | F85: =-18494-1471 -> -19965 | G85: ='Depreciation schedule'!G81 -> -19965 | H85: ='Depreciation schedule'!H81 -> -21475.514 | I85: ='Depreciation schedule'!I81 -> 0 | J85: ='Depreciation schedule'!J81 -> 0 | K85: ='Depreciation schedule'!K81 -> 0 | L85: ='Depreciation schedule'!L81 -> 0
A86: Net book value | C86: =SUM(C80:C85) -> 280019 | D86: =SUM(D80:D85) -> 262502 | E86: =SUM(E80:E85) -> 242216 | F86: =SUM(F80:F85) -> 222251 | G86: ='Depreciation schedule'!G82 -> 321090.39 | H86: ='Depreciation schedule'!H82 -> 299204.62 | I86: ='Depreciation schedule'!I82 -> 438298.27 | J86: ='Depreciation schedule'!J82 -> 441150.05 | K86: ='Depreciation schedule'!K82 -> 440500.76 | L86: ='Depreciation schedule'!L82 -> 606794.32
A87: Gross carrying value - As at December 31, Current Year | G87: ='Depreciation schedule'!G83 -> 0 | H87: ='Depreciation schedule'!H83 -> 0 | I87: ='Depreciation schedule'!I83 -> 0 | J87: ='Depreciation schedule'!J83 -> 0 | K87: ='Depreciation schedule'!K83 -> 0 | L87: ='Depreciation schedule'!L83 -> 0
A88: Cost | C88: =C75+C81 -> 607542 | D88: =D75-98288+100287 -> 609541 | E88: =SUM(397975,26122,50023,100287,33849) -> 608256 | F88: =F75 -> 608256 | G88: ='Depreciation schedule'!G84 -> 728039.39 | H88: ='Depreciation schedule'!H84 -> 726504.58 | I88: ='Depreciation schedule'!I84 -> 866722.78 | J88: ='Depreciation schedule'!J84 -> 869574.57 | K88: ='Depreciation schedule'!K84 -> 867741.38 | L88: ='Depreciation schedule'!L84 -> 1035218.8
A89: Accumulated depreciation | C89: =-SUM(258471,25029,24056,253,19714) -> -327523 | D89: =-SUM(271337,25374,25823,3300,21185) -> -347019 | E89: =-SUM(283420,25719,29778,4467,22656) -> -366040 | F89: =-361878-24127 -> -386005 | G89: ='Depreciation schedule'!G85 -> -406949 | H89: ='Depreciation schedule'!H85 -> -428424.51 | I89: ='Depreciation schedule'!I85 -> -428424.51 | J89: ='Depreciation schedule'!J85 -> -428424.51 | K89: ='Depreciation schedule'!K85 -> -428424.51 | L89: ='Depreciation schedule'!L85 -> -428424.51
A90: Net book value | C90: =SUM(C88:C89) -> 280019 | D90: =SUM(D88:D89) -> 262522 | E90: =SUM(E88:E89) -> 242216 | F90: =SUM(F88:F89) -> 222251 | G90: ='Depreciation schedule'!G86 -> 321090.39 | H90: ='Depreciation schedule'!H86 -> 298080.06 | I90: ='Depreciation schedule'!I86 -> 438298.27 | J90: ='Depreciation schedule'!J86 -> 441150.05 | K90: ='Depreciation schedule'!K86 -> 439316.86 | L90: ='Depreciation schedule'!L86 -> 606794.32
A92: Furnitures, Fixtures and Equipment
A93: Gross carrying value - As at January 1,(Current Year)
A94: Cost | C94: 313611 | D94: 391517 | E94: 429465 | F94: 497747 | G94: 632100 | H94: ='Depreciation schedule'!H91 -> 719772 | I94: ='Depreciation schedule'!I91 -> 954852.23 | J94: ='Depreciation schedule'!J91 -> 1136191.8 | K94: ='Depreciation schedule'!K91 -> 1441066.3 | L94: ='Depreciation schedule'!L91 -> 1638760.8
A95: Accumulated depreciation | C95: -211409 | D95: -244804 | E95: -209813 | F95: -252281 | G95: -330208 | H95: ='Depreciation schedule'!H92 -> -424310 | I95: ='Depreciation schedule'!I92 -> -520905.26 | J95: ='Depreciation schedule'!J92 -> -644588.07 | K95: ='Depreciation schedule'!K92 -> -817373.06 | L95: ='Depreciation schedule'!L92 -> -1010739.6
A96: Net book value | C96: =SUM(C94:C95) -> 102202 | D96: =SUM(D94:D95) -> 146713 | E96: =SUM(E94:E95) -> 219652 | F96: =SUM(F94:F95) -> 245466 | G96: =SUM(G94:G95) -> 301892 | H96: ='Depreciation schedule'!H93 -> 295462 | I96: ='Depreciation schedule'!I93 -> 433946.97 | J96: ='Depreciation schedule'!J93 -> 491603.71 | K96: ='Depreciation schedule'!K93 -> 623693.19 | L96: ='Depreciation schedule'!L93 -> 628021.22
A97: Year ended December 31, Current | H97: ='Depreciation schedule'!H94 -> 0 | I97: ='Depreciation schedule'!I94 -> 0 | J97: ='Depreciation schedule'!J94 -> 0 | K97: ='Depreciation schedule'!K94 -> 0 | L97: ='Depreciation schedule'!L94 -> 0
A98: Net carrying value | H98: ='Depreciation schedule'!H95 -> 0 | I98: ='Depreciation schedule'!I95 -> 0 | J98: ='Depreciation schedule'!J95 -> 0 | K98: ='Depreciation schedule'!K95 -> 0 | L98: ='Depreciation schedule'!L95 -> 0
A99: Opening net book value | C99: =C96 -> 102202 | D99: 146713 | E99: =E96 -> 219652 | F99: 245466 | G99: 301892 | H99: ='Depreciation schedule'!H96 -> 295462 | I99: ='Depreciation schedule'!I96 -> 433946.97 | J99: ='Depreciation schedule'!J96 -> 491603.71 | K99: ='Depreciation schedule'!K96 -> 623693.19 | L99: ='Depreciation schedule'!L96 -> 628021.22
A100: Additions | C100: 81726 | D100: 145239 | E100: 98451 | F100: 143901 | G100: 96493 | H100: ='Depreciation schedule'!H97 -> 267010.03 | I100: ='Depreciation schedule'!I97 -> 218891.31 | J100: ='Depreciation schedule'!J97 -> 328478.39 | K100: ='Depreciation schedule'!K97 -> 219985.46 | L100: ='Depreciation schedule'!L97 -> 607922.47
